image_quaternion/__init__.py
image_quaternion/image_quaternion.py
image_quaternion-0.1.3.dist-info/METADATA
image_quaternion-0.1.3.dist-info/WHEEL
image_quaternion-0.1.3.dist-info/top_level.txt
image_quaternion-0.1.3.dist-info/RECORD
