Metadata-Version: 2.1
Name: image-quaternion
Version: 0.1.3
Summary: Una librería para trabajar con imágenes en formato de cuaterniones.
Home-page: https://github.com/tu_usuario/image_quaternion
Author: Ramiro Esquivel Felix, Luis Octavio Solis Sanchez
Author-email: resfera@gmail.com
Classifier: Programming Language :: Python :: 3
Classifier: License :: OSI Approved :: MIT License
Classifier: Operating System :: OS Independent
Requires-Python: >=3.6
Requires-Dist: numpy
Requires-Dist: matplotlib
Requires-Dist: opencv-python
